README.md
setup.cfg
setup.py
pytest_shard/__init__.py
pytest_shard/pytest_shard.py
pytest_shard.egg-info/PKG-INFO
pytest_shard.egg-info/SOURCES.txt
pytest_shard.egg-info/dependency_links.txt
pytest_shard.egg-info/entry_points.txt
pytest_shard.egg-info/requires.txt
pytest_shard.egg-info/top_level.txt